[ {
  "team_id" : 924,
  "team_name" : "Duisburg WFC",
  "lineup" : [ {
    "player_id" : 10135,
    "player_name" : "Ingibjörg Sigurðardóttir",
    "player_nickname" : null,
    "jersey_number" : 25,
    "country" : {
      "id" : 104,
      "name" : "Iceland"
    },
    "cards" : [ ],
    "positions" : [ {
      "position_id" : 3,
      "position" : "Right Center Back",
      "from" : "00:00",
      "to" : null,
      "from_period" : 1,
      "to_period" : null,
      "start_reason" : "Starting XI",
      "end_reason" : "Final Whistle"
    } ]
  }, {
    "player_id" : 46944,
    "player_name" : "Vanessa Fürst",
    "player_nickname" : null,
    "jersey_number" : 8,
    "country" : {
      "id" : 85,
      "name" : "Germany"
    },
    "cards" : [ ],
    "positions" : [ {
      "position_id" : 2,
      "position" : "Right Back",
      "from" : "00:00",
      "to" : null,
      "from_period" : 1,
      "to_period" : null,
      "start_reason" : "Starting XI",
      "end_reason" : "Final Whistle"
    } ]
  }, {
    "player_id" : 46947,
    "player_name" : "Yvonne Zielinski",
    "player_nickname" : null,
    "jersey_number" : 17,
    "country" : {
      "id" : 85,
      "name" : "Germany"
    },
    "cards" : [ ],
    "positions" : [ {
      "position_id" : 21,
      "position" : "Left Wing",
      "from" : "00:00",
      "to" : "63:44",
      "from_period" : 1,
      "to_period" : 2,
      "start_reason" : "Starting XI",
      "end_reason" : "Substitution - Off (Tactical)"
    } ]
  }, {
    "player_id" : 46952,
    "player_name" : "Miray Cin",
    "player_nickname" : null,
    "jersey_number" : 7,
    "country" : {
      "id" : 233,
      "name" : "Turkey"
    },
    "cards" : [ ],
    "positions" : [ {
      "position_id" : 19,
      "position" : "Center Attacking Midfield",
      "from" : "00:00",
      "to" : "45:00",
      "from_period" : 1,
      "to_period" : 2,
      "start_reason" : "Starting XI",
      "end_reason" : "Tactical Shift"
    }, {
      "position_id" : 9,
      "position" : "Right Defensive Midfield",
      "from" : "45:00",
      "to" : null,
      "from_period" : 2,
      "to_period" : null,
      "start_reason" : "Tactical Shift",
      "end_reason" : "Final Whistle"
    } ]
  }, {
    "player_id" : 47029,
    "player_name" : "Jana Radosavljević",
    "player_nickname" : null,
    "jersey_number" : 6,
    "country" : {
      "id" : 203,
      "name" : "Serbia"
    },
    "cards" : [ ],
    "positions" : [ ]
  }, {
    "player_id" : 49865,
    "player_name" : "Ena Mahmutovic",
    "player_nickname" : null,
    "jersey_number" : 1,
    "country" : {
      "id" : 85,
      "name" : "Germany"
    },
    "cards" : [ {
      "time" : "40:04",
      "card_type" : "Yellow Card",
      "reason" : "Foul Committed",
      "period" : 1
    } ],
    "positions" : [ {
      "position_id" : 1,
      "position" : "Goalkeeper",
      "from" : "00:00",
      "to" : null,
      "from_period" : 1,
      "to_period" : null,
      "start_reason" : "Starting XI",
      "end_reason" : "Final Whistle"
    } ]
  }, {
    "player_id" : 85504,
    "player_name" : "Lisa Josten",
    "player_nickname" : null,
    "jersey_number" : 24,
    "country" : {
      "id" : 85,
      "name" : "Germany"
    },
    "cards" : [ ],
    "positions" : [ {
      "position_id" : 11,
      "position" : "Left Defensive Midfield",
      "from" : "72:10",
      "to" : "72:14",
      "from_period" : 2,
      "to_period" : 2,
      "start_reason" : "Substitution - On (Tactical)",
      "end_reason" : "Tactical Shift"
    }, {
      "position_id" : 24,
      "position" : "Left Center Forward",
      "from" : "72:14",
      "to" : null,
      "from_period" : 2,
      "to_period" : null,
      "start_reason" : "Tactical Shift",
      "end_reason" : "Final Whistle"
    } ]
  }, {
    "player_id" : 96222,
    "player_name" : "Natalie Rose Muth",
    "player_nickname" : null,
    "jersey_number" : 13,
    "country" : {
      "id" : 241,
      "name" : "United States of America"
    },
    "cards" : [ ],
    "positions" : [ {
      "position_id" : 9,
      "position" : "Right Defensive Midfield",
      "from" : "00:00",
      "to" : "45:00",
      "from_period" : 1,
      "to_period" : 2,
      "start_reason" : "Starting XI",
      "end_reason" : "Substitution - Off (Tactical)"
    } ]
  }, {
    "player_id" : 324165,
    "player_name" : "Jil Frehse",
    "player_nickname" : null,
    "jersey_number" : 22,
    "country" : {
      "id" : 85,
      "name" : "Germany"
    },
    "cards" : [ ],
    "positions" : [ ]
  }, {
    "player_id" : 324751,
    "player_name" : "Kara Bathmann",
    "player_nickname" : null,
    "jersey_number" : 4,
    "country" : {
      "id" : 85,
      "name" : "Germany"
    },
    "cards" : [ ],
    "positions" : [ {
      "position_id" : 17,
      "position" : "Right Wing",
      "from" : "45:00",
      "to" : "45:00",
      "from_period" : 2,
      "to_period" : 2,
      "start_reason" : "Tactical Shift",
      "end_reason" : "Substitution - On (Tactical)"
    }, {
      "position_id" : 9,
      "position" : "Right Defensive Midfield",
      "from" : "45:00",
      "to" : "72:14",
      "from_period" : 2,
      "to_period" : 2,
      "start_reason" : "Substitution - On (Tactical)",
      "end_reason" : "Tactical Shift"
    }, {
      "position_id" : 12,
      "position" : "Right Midfield",
      "from" : "72:14",
      "to" : null,
      "from_period" : 2,
      "to_period" : null,
      "start_reason" : "Tactical Shift",
      "end_reason" : "Final Whistle"
    } ]
  }, {
    "player_id" : 325074,
    "player_name" : "Alexandria Loy Hess",
    "player_nickname" : null,
    "jersey_number" : 20,
    "country" : {
      "id" : 241,
      "name" : "United States of America"
    },
    "cards" : [ ],
    "positions" : [ {
      "position_id" : 11,
      "position" : "Left Defensive Midfield",
      "from" : "00:00",
      "to" : "72:10",
      "from_period" : 1,
      "to_period" : 2,
      "start_reason" : "Starting XI",
      "end_reason" : "Substitution - Off (Tactical)"
    } ]
  }, {
    "player_id" : 325076,
    "player_name" : "Gina Ebels",
    "player_nickname" : null,
    "jersey_number" : 30,
    "country" : {
      "id" : 85,
      "name" : "Germany"
    },
    "cards" : [ ],
    "positions" : [ ]
  }, {
    "player_id" : 325077,
    "player_name" : "Paula Flach",
    "player_nickname" : null,
    "jersey_number" : 5,
    "country" : {
      "id" : 85,
      "name" : "Germany"
    },
    "cards" : [ ],
    "positions" : [ {
      "position_id" : 6,
      "position" : "Left Back",
      "from" : "00:00",
      "to" : null,
      "from_period" : 1,
      "to_period" : null,
      "start_reason" : "Starting XI",
      "end_reason" : "Final Whistle"
    } ]
  }, {
    "player_id" : 325078,
    "player_name" : "Sarah Freutel",
    "player_nickname" : null,
    "jersey_number" : 21,
    "country" : {
      "id" : 85,
      "name" : "Germany"
    },
    "cards" : [ ],
    "positions" : [ {
      "position_id" : 17,
      "position" : "Right Wing",
      "from" : "00:00",
      "to" : "45:00",
      "from_period" : 1,
      "to_period" : 2,
      "start_reason" : "Starting XI",
      "end_reason" : "Substitution - Off (Tactical)"
    } ]
  }, {
    "player_id" : 389568,
    "player_name" : "Taryn Ries",
    "player_nickname" : null,
    "jersey_number" : 9,
    "country" : {
      "id" : 241,
      "name" : "United States of America"
    },
    "cards" : [ ],
    "positions" : [ {
      "position_id" : 23,
      "position" : "Center Forward",
      "from" : "00:00",
      "to" : "72:14",
      "from_period" : 1,
      "to_period" : 2,
      "start_reason" : "Starting XI",
      "end_reason" : "Tactical Shift"
    }, {
      "position_id" : 22,
      "position" : "Right Center Forward",
      "from" : "72:14",
      "to" : null,
      "from_period" : 2,
      "to_period" : null,
      "start_reason" : "Tactical Shift",
      "end_reason" : "Final Whistle"
    } ]
  }, {
    "player_id" : 408984,
    "player_name" : "Jelena Prvulovic",
    "player_nickname" : null,
    "jersey_number" : 18,
    "country" : {
      "id" : 15,
      "name" : "Austria"
    },
    "cards" : [ ],
    "positions" : [ {
      "position_id" : 19,
      "position" : "Center Attacking Midfield",
      "from" : "45:00",
      "to" : "45:00",
      "from_period" : 2,
      "to_period" : 2,
      "start_reason" : "Tactical Shift",
      "end_reason" : "Substitution - On (Tactical)"
    }, {
      "position_id" : 17,
      "position" : "Right Wing",
      "from" : "45:00",
      "to" : "72:14",
      "from_period" : 2,
      "to_period" : 2,
      "start_reason" : "Substitution - On (Tactical)",
      "end_reason" : "Tactical Shift"
    }, {
      "position_id" : 11,
      "position" : "Left Defensive Midfield",
      "from" : "72:14",
      "to" : null,
      "from_period" : 2,
      "to_period" : null,
      "start_reason" : "Tactical Shift",
      "end_reason" : "Final Whistle"
    } ]
  }, {
    "player_id" : 408987,
    "player_name" : "Samantha Jerabek",
    "player_nickname" : null,
    "jersey_number" : 16,
    "country" : {
      "id" : 241,
      "name" : "United States of America"
    },
    "cards" : [ ],
    "positions" : [ {
      "position_id" : 21,
      "position" : "Left Wing",
      "from" : "63:44",
      "to" : "72:14",
      "from_period" : 2,
      "to_period" : 2,
      "start_reason" : "Substitution - On (Tactical)",
      "end_reason" : "Tactical Shift"
    }, {
      "position_id" : 16,
      "position" : "Left Midfield",
      "from" : "72:14",
      "to" : null,
      "from_period" : 2,
      "to_period" : null,
      "start_reason" : "Tactical Shift",
      "end_reason" : "Final Whistle"
    } ]
  }, {
    "player_id" : 408989,
    "player_name" : "Jeleaugh Rosa",
    "player_nickname" : null,
    "jersey_number" : 2,
    "country" : {
      "id" : 58,
      "name" : "Curaçao"
    },
    "cards" : [ ],
    "positions" : [ ]
  }, {
    "player_id" : 423620,
    "player_name" : "Haley Marie Thomas",
    "player_nickname" : null,
    "jersey_number" : 3,
    "country" : {
      "id" : 241,
      "name" : "United States of America"
    },
    "cards" : [ ],
    "positions" : [ {
      "position_id" : 5,
      "position" : "Left Center Back",
      "from" : "00:00",
      "to" : null,
      "from_period" : 1,
      "to_period" : null,
      "start_reason" : "Starting XI",
      "end_reason" : "Final Whistle"
    } ]
  } ]
}, {
  "team_id" : 19107,
  "team_name" : "RB Leipzig W",
  "lineup" : [ {
    "player_id" : 10665,
    "player_name" : "Mimmi Wahlström",
    "player_nickname" : null,
    "jersey_number" : 14,
    "country" : {
      "id" : 220,
      "name" : "Sweden"
    },
    "cards" : [ ],
    "positions" : [ {
      "position_id" : 24,
      "position" : "Left Center Forward",
      "from" : "00:00",
      "to" : "75:30",
      "from_period" : 1,
      "to_period" : 2,
      "start_reason" : "Starting XI",
      "end_reason" : "Tactical Shift"
    }, {
      "position_id" : 22,
      "position" : "Right Center Forward",
      "from" : "75:30",
      "to" : "89:37",
      "from_period" : 2,
      "to_period" : 2,
      "start_reason" : "Tactical Shift",
      "end_reason" : "Substitution - Off (Tactical)"
    } ]
  }, {
    "player_id" : 32087,
    "player_name" : "Lydia Andrade",
    "player_nickname" : null,
    "jersey_number" : 17,
    "country" : {
      "id" : 221,
      "name" : "Switzerland"
    },
    "cards" : [ ],
    "positions" : [ {
      "position_id" : 12,
      "position" : "Right Midfield",
      "from" : "00:00",
      "to" : "65:15",
      "from_period" : 1,
      "to_period" : 2,
      "start_reason" : "Starting XI",
      "end_reason" : "Substitution - Off (Tactical)"
    } ]
  }, {
    "player_id" : 46557,
    "player_name" : "Barbara Brecht",
    "player_nickname" : null,
    "jersey_number" : 11,
    "country" : {
      "id" : 85,
      "name" : "Germany"
    },
    "cards" : [ ],
    "positions" : [ {
      "position_id" : 22,
      "position" : "Right Center Forward",
      "from" : "45:00",
      "to" : "45:00",
      "from_period" : 2,
      "to_period" : 2,
      "start_reason" : "Tactical Shift",
      "end_reason" : "Substitution - On (Tactical)"
    }, {
      "position_id" : 16,
      "position" : "Left Midfield",
      "from" : "45:00",
      "to" : null,
      "from_period" : 2,
      "to_period" : null,
      "start_reason" : "Substitution - On (Tactical)",
      "end_reason" : "Final Whistle"
    } ]
  }, {
    "player_id" : 46559,
    "player_name" : "Nina Räcke",
    "player_nickname" : null,
    "jersey_number" : 4,
    "country" : {
      "id" : 85,
      "name" : "Germany"
    },
    "cards" : [ ],
    "positions" : [ {
      "position_id" : 6,
      "position" : "Left Back",
      "from" : "79:39",
      "to" : "80:13",
      "from_period" : 2,
      "to_period" : 2,
      "start_reason" : "Substitution - On (Tactical)",
      "end_reason" : "Tactical Shift"
    }, {
      "position_id" : 3,
      "position" : "Right Center Back",
      "from" : "80:13",
      "to" : null,
      "from_period" : 2,
      "to_period" : null,
      "start_reason" : "Tactical Shift",
      "end_reason" : "Final Whistle"
    } ]
  }, {
    "player_id" : 46893,
    "player_name" : "Gianna Rackow",
    "player_nickname" : null,
    "jersey_number" : 8,
    "country" : {
      "id" : 85,
      "name" : "Germany"
    },
    "cards" : [ ],
    "positions" : [ {
      "position_id" : 16,
      "position" : "Left Midfield",
      "from" : "00:00",
      "to" : "45:00",
      "from_period" : 1,
      "to_period" : 2,
      "start_reason" : "Starting XI",
      "end_reason" : "Substitution - Off (Tactical)"
    } ]
  }, {
    "player_id" : 46896,
    "player_name" : "Elvira Herzog",
    "player_nickname" : null,
    "jersey_number" : 12,
    "country" : {
      "id" : 221,
      "name" : "Switzerland"
    },
    "cards" : [ ],
    "positions" : [ {
      "position_id" : 1,
      "position" : "Goalkeeper",
      "from" : "00:00",
      "to" : null,
      "from_period" : 1,
      "to_period" : null,
      "start_reason" : "Starting XI",
      "end_reason" : "Final Whistle"
    } ]
  }, {
    "player_id" : 46980,
    "player_name" : "Luca Maria Graf",
    "player_nickname" : null,
    "jersey_number" : 26,
    "country" : {
      "id" : 85,
      "name" : "Germany"
    },
    "cards" : [ ],
    "positions" : [ {
      "position_id" : 9,
      "position" : "Right Defensive Midfield",
      "from" : "00:00",
      "to" : null,
      "from_period" : 1,
      "to_period" : null,
      "start_reason" : "Starting XI",
      "end_reason" : "Final Whistle"
    } ]
  }, {
    "player_id" : 47106,
    "player_name" : "Julia Pollak",
    "player_nickname" : null,
    "jersey_number" : 29,
    "country" : {
      "id" : 85,
      "name" : "Germany"
    },
    "cards" : [ {
      "time" : "57:46",
      "card_type" : "Yellow Card",
      "reason" : "Foul Committed",
      "period" : 2
    } ],
    "positions" : [ {
      "position_id" : 5,
      "position" : "Left Center Back",
      "from" : "00:00",
      "to" : "80:13",
      "from_period" : 1,
      "to_period" : 2,
      "start_reason" : "Starting XI",
      "end_reason" : "Tactical Shift"
    }, {
      "position_id" : 6,
      "position" : "Left Back",
      "from" : "80:13",
      "to" : null,
      "from_period" : 2,
      "to_period" : null,
      "start_reason" : "Tactical Shift",
      "end_reason" : "Final Whistle"
    } ]
  }, {
    "player_id" : 49045,
    "player_name" : "Victoria Krug",
    "player_nickname" : null,
    "jersey_number" : 20,
    "country" : {
      "id" : 85,
      "name" : "Germany"
    },
    "cards" : [ ],
    "positions" : [ {
      "position_id" : 3,
      "position" : "Right Center Back",
      "from" : "00:00",
      "to" : "80:13",
      "from_period" : 1,
      "to_period" : 2,
      "start_reason" : "Starting XI",
      "end_reason" : "Tactical Shift"
    }, {
      "position_id" : 5,
      "position" : "Left Center Back",
      "from" : "80:13",
      "to" : "89:45",
      "from_period" : 2,
      "to_period" : 2,
      "start_reason" : "Tactical Shift",
      "end_reason" : "Substitution - Off (Tactical)"
    } ]
  }, {
    "player_id" : 409145,
    "player_name" : "Michela Croatto",
    "player_nickname" : null,
    "jersey_number" : 16,
    "country" : {
      "id" : 15,
      "name" : "Austria"
    },
    "cards" : [ {
      "time" : "65:42",
      "card_type" : "Yellow Card",
      "reason" : "Foul Committed",
      "period" : 2
    } ],
    "positions" : [ {
      "position_id" : 6,
      "position" : "Left Back",
      "from" : "00:00",
      "to" : "74:03",
      "from_period" : 1,
      "to_period" : 2,
      "start_reason" : "Starting XI",
      "end_reason" : "Player Off"
    }, {
      "position_id" : 6,
      "position" : "Left Back",
      "from" : "75:02",
      "to" : "79:39",
      "from_period" : 2,
      "to_period" : 2,
      "start_reason" : "Player On",
      "end_reason" : "Substitution - Off (Tactical)"
    } ]
  }, {
    "player_id" : 409146,
    "player_name" : "Julia Magerl",
    "player_nickname" : null,
    "jersey_number" : 15,
    "country" : {
      "id" : 15,
      "name" : "Austria"
    },
    "cards" : [ ],
    "positions" : [ {
      "position_id" : 5,
      "position" : "Left Center Back",
      "from" : "89:45",
      "to" : null,
      "from_period" : 2,
      "to_period" : null,
      "start_reason" : "Substitution - On (Tactical)",
      "end_reason" : "Final Whistle"
    } ]
  }, {
    "player_id" : 409150,
    "player_name" : "Gina Schüller",
    "player_nickname" : null,
    "jersey_number" : 1,
    "country" : {
      "id" : 85,
      "name" : "Germany"
    },
    "cards" : [ ],
    "positions" : [ ]
  }, {
    "player_id" : 409152,
    "player_name" : "Jenny Hipp",
    "player_nickname" : null,
    "jersey_number" : 19,
    "country" : {
      "id" : 85,
      "name" : "Germany"
    },
    "cards" : [ ],
    "positions" : [ {
      "position_id" : 11,
      "position" : "Left Defensive Midfield",
      "from" : "00:00",
      "to" : null,
      "from_period" : 1,
      "to_period" : null,
      "start_reason" : "Starting XI",
      "end_reason" : "Final Whistle"
    } ]
  }, {
    "player_id" : 409153,
    "player_name" : "Korina Lara Janež",
    "player_nickname" : "Korina Janež",
    "jersey_number" : 7,
    "country" : {
      "id" : 208,
      "name" : "Slovenia"
    },
    "cards" : [ ],
    "positions" : [ {
      "position_id" : 22,
      "position" : "Right Center Forward",
      "from" : "89:37",
      "to" : null,
      "from_period" : 2,
      "to_period" : null,
      "start_reason" : "Substitution - On (Tactical)",
      "end_reason" : "Final Whistle"
    } ]
  }, {
    "player_id" : 409155,
    "player_name" : "Marlene Müller",
    "player_nickname" : null,
    "jersey_number" : 27,
    "country" : {
      "id" : 85,
      "name" : "Germany"
    },
    "cards" : [ ],
    "positions" : [ {
      "position_id" : 2,
      "position" : "Right Back",
      "from" : "00:00",
      "to" : null,
      "from_period" : 1,
      "to_period" : null,
      "start_reason" : "Starting XI",
      "end_reason" : "Final Whistle"
    } ]
  }, {
    "player_id" : 409156,
    "player_name" : "Vanessa Fudalla",
    "player_nickname" : null,
    "jersey_number" : 10,
    "country" : {
      "id" : 85,
      "name" : "Germany"
    },
    "cards" : [ ],
    "positions" : [ {
      "position_id" : 22,
      "position" : "Right Center Forward",
      "from" : "00:00",
      "to" : "45:00",
      "from_period" : 1,
      "to_period" : 2,
      "start_reason" : "Starting XI",
      "end_reason" : "Tactical Shift"
    }, {
      "position_id" : 16,
      "position" : "Left Midfield",
      "from" : "45:00",
      "to" : "75:30",
      "from_period" : 2,
      "to_period" : 2,
      "start_reason" : "Tactical Shift",
      "end_reason" : "Tactical Shift"
    }, {
      "position_id" : 24,
      "position" : "Left Center Forward",
      "from" : "75:30",
      "to" : null,
      "from_period" : 2,
      "to_period" : null,
      "start_reason" : "Tactical Shift",
      "end_reason" : "Final Whistle"
    } ]
  }, {
    "player_id" : 415551,
    "player_name" : "Mia Werner",
    "player_nickname" : null,
    "jersey_number" : 32,
    "country" : {
      "id" : 85,
      "name" : "Germany"
    },
    "cards" : [ ],
    "positions" : [ {
      "position_id" : 12,
      "position" : "Right Midfield",
      "from" : "65:15",
      "to" : null,
      "from_period" : 2,
      "to_period" : null,
      "start_reason" : "Substitution - On (Tactical)",
      "end_reason" : "Final Whistle"
    } ]
  }, {
    "player_id" : 429339,
    "player_name" : "Rucy Grunenberg",
    "player_nickname" : "R.Grunenberg",
    "jersey_number" : 34,
    "country" : {
      "id" : 85,
      "name" : "Germany"
    },
    "cards" : [ ],
    "positions" : [ ]
  } ]
} ]